psplit.py
psplit-1.0.4.dist-info/LICENSE
psplit-1.0.4.dist-info/METADATA
psplit-1.0.4.dist-info/WHEEL
psplit-1.0.4.dist-info/entry_points.txt
psplit-1.0.4.dist-info/RECORD
