Metadata-Version: 2.1
Name: psplit
Version: 1.0.4
Summary: ✂️ Split git patch files ✂️
License: MIT
Author: Tom Ritchford
Author-email: tom@swirly.com
Requires-Python: >=3.9,<4.0
Classifier: License :: OSI Approved :: MIT License
Classifier: Programming Language :: Python :: 3
Classifier: Programming Language :: Python :: 3.9
Classifier: Programming Language :: Python :: 3.10
Classifier: Programming Language :: Python :: 3.11
Classifier: Programming Language :: Python :: 3.12
Classifier: Programming Language :: Python :: 3.13
